[
  {
    "Case_Number": "Suit 798/2007",
    "Plaintiff": "ABB Holdings Pte Ltd",
    "Defendant": "Sher Hock Guan Charles",
    "Plaintiff_Label": "Claim Dismissed",
    "Defendant_Label": "Not Liable"
  },
  {
    "Case_Number": "Suit 798/2007",
    "Plaintiff": "ABB Installation Materials (East Asia) Pte Ltd",
    "Defendant": "Sher Hock Guan Charles",
    "Plaintiff_Label": "Claim Allowed In-part",
    "Defendant_Label": "Liable"
  },
  {
    "Case_Number": "Suit 798/2007",
    "Plaintiff": "ABB Industry Pte Ltd",
    "Defendant": "Sher Hock Guan Charles",
    "Plaintiff_Label": "Claim Allowed In-part",
    "Defendant_Label": "Liable"
  }
]